nercone_macpower/__init__.py
nercone_macpower/__main__.py
nercone_macpower/macpower.py
nercone_macpower-0.3.2.dist-info/WHEEL
nercone_macpower-0.3.2.dist-info/entry_points.txt
nercone_macpower-0.3.2.dist-info/METADATA
nercone_macpower-0.3.2.dist-info/RECORD
