Metadata-Version: 2.3
Name: nercone-macpower
Version: 0.3.2
Summary: pmset wrapper library/cli app for Python on macOS
Author: Nercone
Author-email: Nercone <nercone@diamondgotcat.net>
License: MIT
Classifier: Programming Language :: Python :: 3
Classifier: License :: OSI Approved :: MIT License
Classifier: Operating System :: MacOS
Requires-Dist: rich
Requires-Python: >=3.8
